arrakis/__init__.py
arrakis/__main__.py
arrakis/_version.py
arrakis/api.py
arrakis/block.py
arrakis/channel.py
arrakis/client.py
arrakis/constants.py
arrakis/flight.py
arrakis/mux.py
arrakis/publish.py
arrakis/py.typed
arrakis/tests/__init__.py
arrakis/tests/integration/conftest.py
arrakis/tests/integration/test_api.py
arrakis/tests/integration/test_cli.py
arrakis/tests/integration/data/channels.toml
arrakis/tests/unit/__init__.py
arrakis/tests/unit/test_block.py
arrakis/tests/unit/test_channel.py
arrakis/tests/unit/test_cli.py
arrakis/tests/unit/test_client.py
arrakis/tests/unit/test_mux.py
arrakis/tests/unit/test_publish.py
arrakis/tests/unit/test_request.py
arrakis-0.6.1.dist-info/METADATA
arrakis-0.6.1.dist-info/WHEEL
arrakis-0.6.1.dist-info/entry_points.txt
arrakis-0.6.1.dist-info/licenses/AUTHORS.md
arrakis-0.6.1.dist-info/licenses/LICENSE
arrakis-0.6.1.dist-info/RECORD
