Metadata-Version: 2.4
Name: arrakis
Version: 0.6.1
Summary: Arrakis Python client library
Project-URL: Homepage, https://git.ligo.org/ngdd/arrakis-python
Project-URL: Documentation, https://docs.ligo.org/ngdd/arrakis-python
Project-URL: Issue Tracker, https://git.ligo.org/ngdd/arrakis-python/issues
Project-URL: Source Code, https://git.ligo.org/ngdd/arrakis-python.git
Author-email: Patrick Godwin <patrick.godwin@ligo.org>, Jameson Graef Rollins <jameson.rollins@ligo.org>
Maintainer-email: Patrick Godwin <patrick.godwin@ligo.org>
License-Expression: LGPL-3.0-or-later
License-File: AUTHORS.md
License-File: LICENSE
Classifier: Development Status :: 3 - Alpha
Classifier: Intended Audience :: Developers
Classifier: Intended Audience :: Science/Research
Classifier: License :: OSI Approved :: GNU General Public License v3 or later (GPLv3+)
Classifier: Natural Language :: English
Classifier: Operating System :: POSIX
Classifier: Operating System :: POSIX :: Linux
Classifier: Programming Language :: Python
Classifier: Programming Language :: Python :: 3
Classifier: Topic :: Scientific/Engineering
Classifier: Topic :: Scientific/Engineering :: Astronomy
Classifier: Topic :: Scientific/Engineering :: Physics
Requires-Python: >=3.10
Requires-Dist: arrakis-schema>=0.2
Requires-Dist: gpstime
Requires-Dist: jsonschema
Requires-Dist: numpy
Requires-Dist: pyarrow
Requires-Dist: typing-extensions
Provides-Extra: dev
Requires-Dist: arrakis-server>=0.5; (python_version >= '3.11') and extra == 'dev'
Requires-Dist: markdown-callouts>=0.2; extra == 'dev'
Requires-Dist: markdown-exec>=0.5; extra == 'dev'
Requires-Dist: mkdocs-coverage>=0.2; extra == 'dev'
Requires-Dist: mkdocs-gen-files>=0.3; extra == 'dev'
Requires-Dist: mkdocs-literate-nav>=0.4; extra == 'dev'
Requires-Dist: mkdocs-material-igwn; extra == 'dev'
Requires-Dist: mkdocs-section-index>=0.3; extra == 'dev'
Requires-Dist: mkdocs>=1.3; extra == 'dev'
Requires-Dist: mkdocstrings[python]; extra == 'dev'
Requires-Dist: mockafka-py; extra == 'dev'
Requires-Dist: mypy; extra == 'dev'
Requires-Dist: mypy-extensions; extra == 'dev'
Requires-Dist: pip; extra == 'dev'
Requires-Dist: pytest; extra == 'dev'
Requires-Dist: pytest-console-scripts; extra == 'dev'
Requires-Dist: pytest-cov; extra == 'dev'
Requires-Dist: pytest-freezer; extra == 'dev'
Requires-Dist: ruff; extra == 'dev'
Requires-Dist: toml>=0.10; extra == 'dev'
Provides-Extra: docs
Requires-Dist: markdown-callouts>=0.2; extra == 'docs'
Requires-Dist: markdown-exec>=0.5; extra == 'docs'
Requires-Dist: mkdocs-coverage>=0.2; extra == 'docs'
Requires-Dist: mkdocs-gen-files>=0.3; extra == 'docs'
Requires-Dist: mkdocs-literate-nav>=0.4; extra == 'docs'
Requires-Dist: mkdocs-material-igwn; extra == 'docs'
Requires-Dist: mkdocs-section-index>=0.3; extra == 'docs'
Requires-Dist: mkdocs>=1.3; extra == 'docs'
Requires-Dist: mkdocstrings[python]; extra == 'docs'
Requires-Dist: toml>=0.10; extra == 'docs'
Provides-Extra: lint
Requires-Dist: mypy; extra == 'lint'
Requires-Dist: mypy-extensions; extra == 'lint'
Requires-Dist: pip; extra == 'lint'
Requires-Dist: ruff; extra == 'lint'
Provides-Extra: publish
Requires-Dist: confluent-kafka>=1.8; extra == 'publish'
Requires-Dist: sympy; extra == 'publish'
Provides-Extra: test
Requires-Dist: arrakis-server>=0.5; (python_version >= '3.11') and extra == 'test'
Requires-Dist: mockafka-py; extra == 'test'
Requires-Dist: pytest; extra == 'test'
Requires-Dist: pytest-console-scripts; extra == 'test'
Requires-Dist: pytest-cov; extra == 'test'
Requires-Dist: pytest-freezer; extra == 'test'
